py_selenium_auto_core/__init__.py
py_selenium_auto_core/py.typed
py_selenium_auto_core/applications/__init__.py
py_selenium_auto_core/applications/application.py
py_selenium_auto_core/applications/core_services.py
py_selenium_auto_core/applications/startup.py
py_selenium_auto_core/configurations/__init__.py
py_selenium_auto_core/configurations/base_configurations.py
py_selenium_auto_core/configurations/element_cache_configuration.py
py_selenium_auto_core/configurations/logger_configuration.py
py_selenium_auto_core/configurations/retry_configuration.py
py_selenium_auto_core/configurations/timeout_configuration.py
py_selenium_auto_core/elements/__init__.py
py_selenium_auto_core/elements/cached_element_state_provider.py
py_selenium_auto_core/elements/core_element.py
py_selenium_auto_core/elements/element_cache_handler.py
py_selenium_auto_core/elements/element_factory.py
py_selenium_auto_core/elements/element_finder.py
py_selenium_auto_core/elements/element_state_provider.py
py_selenium_auto_core/elements/constants/__init__.py
py_selenium_auto_core/elements/constants/desired_state.py
py_selenium_auto_core/elements/constants/element_state.py
py_selenium_auto_core/elements/constants/elements_count.py
py_selenium_auto_core/forms/__init__.py
py_selenium_auto_core/forms/core_form.py
py_selenium_auto_core/localization/__init__.py
py_selenium_auto_core/localization/localization_manager.py
py_selenium_auto_core/localization/localized_logger.py
py_selenium_auto_core/locator/__init__.py
py_selenium_auto_core/locator/locator.py
py_selenium_auto_core/logging/__init__.py
py_selenium_auto_core/logging/logger.py
py_selenium_auto_core/resources/settings.json
py_selenium_auto_core/resources/localization/en.json
py_selenium_auto_core/resources/localization/ru.json
py_selenium_auto_core/utilities/__init__.py
py_selenium_auto_core/utilities/action_retrier.py
py_selenium_auto_core/utilities/environment_configuration.py
py_selenium_auto_core/utilities/file_reader.py
py_selenium_auto_core-0.5.6.dist-info/LICENSE
py_selenium_auto_core-0.5.6.dist-info/METADATA
py_selenium_auto_core-0.5.6.dist-info/WHEEL
py_selenium_auto_core-0.5.6.dist-info/top_level.txt
py_selenium_auto_core-0.5.6.dist-info/zip-safe
py_selenium_auto_core-0.5.6.dist-info/RECORD
